LICENSE.txt
MANIFEST.in
build-requirements.txt
pyproject.toml
requirements.txt
arcgis/auth/__init__.py
arcgis/auth/_version.py
arcgis/auth/api.py
arcgis/auth/_auth/__init__.py
arcgis/auth/_auth/_apikey.py
arcgis/auth/_auth/_base.py
arcgis/auth/_auth/_basic.py
arcgis/auth/_auth/_negotiate.py
arcgis/auth/_auth/_notebook.py
arcgis/auth/_auth/_ntlm.py
arcgis/auth/_auth/_oauth.py
arcgis/auth/_auth/_pkce.py
arcgis/auth/_auth/_pki.py
arcgis/auth/_auth/_provided_token.py
arcgis/auth/_auth/_schain.py
arcgis/auth/_auth/_token.py
arcgis/auth/_auth/_utils.py
arcgis/auth/_auth/_winauth.py
arcgis/auth/_error/__init__.py
arcgis/auth/_error/error.py
arcgis/auth/tools/__init__.py
arcgis/auth/tools/_adapter.py
arcgis/auth/tools/_lazy.py
arcgis/auth/tools/_util.py
arcgis/auth/tools/cert.py
arcgis/auth/tools/certificate.py
arcgis/auth/tools/nbauth.py
arcgis/auth/tools/verifycontext.py
arcgis_auth.egg-info/PKG-INFO
arcgis_auth.egg-info/SOURCES.txt
arcgis_auth.egg-info/dependency_links.txt
arcgis_auth.egg-info/requires.txt
arcgis_auth.egg-info/top_level.txt