Metadata-Version: 2.1
Name: arcgis-auth
Version: 1.0.0a0
Summary: Authentication Handlers for the ArcGIS API for Python
Author-email: ArcGIS API for Python Team <support@esri.com>
License: Esri Master License Agreement
Classifier: Development Status :: 5 - Production/Stable
Classifier: Topic :: Software Development :: Libraries :: Python Modules
Classifier: Intended Audience :: Developers
Classifier: Intended Audience :: Science/Research
Classifier: Operating System :: OS Independent
Classifier: License :: Other/Proprietary License
Classifier: Programming Language :: Python :: 3 :: Only
Classifier: Programming Language :: Python :: 3.10
Classifier: Programming Language :: Python :: 3.11
Classifier: Programming Language :: Python :: 3.12
Requires-Python: <3.13,>3.9
License-File: LICENSE.txt
Requires-Dist: urllib3<3,>=2.1.0
Requires-Dist: cachetools
Requires-Dist: lxml
Requires-Dist: cryptography
Requires-Dist: truststore>=0.9.0
Requires-Dist: pywin32>=223; platform_system == "Windows"
Requires-Dist: requests<3,>=2.30.0
Requires-Dist: requests-oauthlib
Requires-Dist: requests_toolbelt
Requires-Dist: pyspnego>=0.8.0
Requires-Dist: requests-kerberos
Requires-Dist: requests-gssapi
